advanced_analysis/__init__.py
advanced_analysis/version.py
advanced_analysis/algorithm_complexity/__init__.py
advanced_analysis/algorithm_complexity/complexity_analyzer.py
advanced_analysis/algorithm_complexity/dynamic_analyzer.py
advanced_analysis/algorithm_complexity/model_analyzer.py
advanced_analysis/algorithm_complexity/model_compression.py
advanced_analysis/algorithm_complexity/static_analyzer.py
advanced_analysis/cloud/__init__.py
advanced_analysis/cloud/cost_optimizer.py
advanced_analysis/cloud/profiler.py
advanced_analysis/data_quality/__init__.py
advanced_analysis/data_quality/guardian.py
advanced_analysis/data_quality/optimizer.py
advanced_analysis/ml_advisor/__init__.py
advanced_analysis/ml_advisor/algorithm_recognition.py
advanced_analysis/ml_advisor/inefficiency_detection.py
advanced_analysis/ml_advisor/jupyter_extension.py
advanced_analysis/ml_advisor/suggestions.py
advanced_analysis/mlops/__init__.py
advanced_analysis/mlops/cicd.py
advanced_analysis/mlops/kubeflow.py
advanced_analysis/mlops/mlflow.py
advanced_analysis/mlops/templates/__init__.py
advanced_analysis/mlops/templates/azure_pipelines_workflow.yml
advanced_analysis/mlops/templates/github_actions_workflow.yml
advanced_analysis/mlops/templates/gitlab_ci_workflow.yml
advanced_analysis/mlops/templates/jenkins_workflow.groovy
advanced_analysis/performance/__init__.py
advanced_analysis/performance/core.py
advanced_analysis/performance/distributed.py
advanced_analysis/performance/roofline.py
advanced_analysis/performance/vectorization.py
advanced_analysis/utils/__init__.py
advanced_analysis/utils/error_handling.py
advanced_analysis/utils/hardware_utils.py
advanced_analysis/visualization/__init__.py
advanced_analysis/visualization/dashboards.py
advanced_analysis/visualization/reports.py
model_sources/__init__.py
model_sources/huggingface.py
model_sources/onnx_zoo.py
model_sources/pytorch_hub.py
model_sources/sagemaker.py
model_sources/tensorflow_hub.py
model_sources/tf_garden.py
neural_scope-0.3.0.dist-info/licenses/LICENSE
neural_scope-0.3.0.dist-info/METADATA
neural_scope-0.3.0.dist-info/WHEEL
neural_scope-0.3.0.dist-info/entry_points.txt
neural_scope-0.3.0.dist-info/top_level.txt
neural_scope-0.3.0.dist-info/RECORD
