Metadata-Version: 2.4
Name: neural-scope
Version: 0.3.0
Summary: A comprehensive tool for analyzing and optimizing machine learning models
Home-page: https://github.com/adil-faiyaz98/neural-scope
Author: Adil Faiyaz
Author-email: adilmd98@gmail.com
Keywords: machine learning,deep learning,model optimization,model analysis,CI/CD,MLflow,security,robustness,adversarial,model registry
Classifier: Development Status :: 4 - Beta
Classifier: Intended Audience :: Developers
Classifier: Intended Audience :: Science/Research
Classifier: License :: OSI Approved :: MIT License
Classifier: Programming Language :: Python :: 3
Classifier: Programming Language :: Python :: 3.7
Classifier: Programming Language :: Python :: 3.8
Classifier: Programming Language :: Python :: 3.9
Classifier: Topic :: Scientific/Engineering
Classifier: Topic :: Scientific/Engineering :: Artificial Intelligence
Classifier: Topic :: Software Development :: Libraries :: Python Modules
Requires-Python: >=3.7
License-File: LICENSE
Requires-Dist: numpy>=1.19.0
Requires-Dist: pandas>=1.1.0
Requires-Dist: matplotlib>=3.3.0
Requires-Dist: seaborn>=0.11.0
Requires-Dist: scikit-learn>=0.23.0
Requires-Dist: tqdm>=4.50.0
Requires-Dist: pyyaml>=5.3.0
Requires-Dist: requests>=2.25.0
Requires-Dist: pillow>=8.0.0
Requires-Dist: jsonschema>=3.2.0
Provides-Extra: pytorch
Requires-Dist: torch>=1.7.0; extra == "pytorch"
Requires-Dist: torchvision>=0.8.0; extra == "pytorch"
Provides-Extra: tensorflow
Requires-Dist: tensorflow>=2.4.0; extra == "tensorflow"
Requires-Dist: tensorflow-hub>=0.10.0; extra == "tensorflow"
Provides-Extra: huggingface
Requires-Dist: transformers>=4.5.0; extra == "huggingface"
Provides-Extra: mlflow
Requires-Dist: mlflow>=1.15.0; extra == "mlflow"
Provides-Extra: onnx
Requires-Dist: onnx>=1.8.0; extra == "onnx"
Requires-Dist: onnxruntime>=1.7.0; extra == "onnx"
Provides-Extra: aws
Requires-Dist: boto3>=1.17.0; extra == "aws"
Requires-Dist: sagemaker>=2.35.0; extra == "aws"
Provides-Extra: security
Requires-Dist: foolbox>=3.3.0; extra == "security"
Requires-Dist: adversarial-robustness-toolbox>=1.9.0; extra == "security"
Provides-Extra: all
Requires-Dist: torch>=1.7.0; extra == "all"
Requires-Dist: torchvision>=0.8.0; extra == "all"
Requires-Dist: tensorflow>=2.4.0; extra == "all"
Requires-Dist: tensorflow-hub>=0.10.0; extra == "all"
Requires-Dist: transformers>=4.5.0; extra == "all"
Requires-Dist: mlflow>=1.15.0; extra == "all"
Requires-Dist: onnx>=1.8.0; extra == "all"
Requires-Dist: onnxruntime>=1.7.0; extra == "all"
Requires-Dist: boto3>=1.17.0; extra == "all"
Requires-Dist: sagemaker>=2.35.0; extra == "all"
Requires-Dist: foolbox>=3.3.0; extra == "all"
Requires-Dist: adversarial-robustness-toolbox>=1.9.0; extra == "all"
Dynamic: author
Dynamic: author-email
Dynamic: classifier
Dynamic: description
Dynamic: description-content-type
Dynamic: home-page
Dynamic: keywords
Dynamic: license-file
Dynamic: provides-extra
Dynamic: requires-dist
Dynamic: requires-python
Dynamic: summary
